fleece/__about__.py
fleece/__init__.py
fleece/authpolicy.py
fleece/boto3.py
fleece/cli/__init__.py
fleece/cli/build/Dockerfile
fleece/cli/build/__init__.py
fleece/cli/build/build.py
fleece/cli/build/docker_build_lambda.sh
fleece/cli/config/__init__.py
fleece/cli/config/config.py
fleece/cli/main.py
fleece/cli/run/__init__.py
fleece/cli/run/run.py
fleece/conftest.py
fleece/connexion.py
fleece/events.py
fleece/handlers/__init__.py
fleece/handlers/connexion.py
fleece/handlers/wsgi.py
fleece/httperror.py
fleece/log.py
fleece/profiling.py
fleece/raxauth.py
fleece/requests.py
fleece/testing.py
fleece/utils.py
fleece/xray.py
fleece-1.2.1.dist-info/entry_points.txt
fleece-1.2.1.dist-info/LICENSE
fleece-1.2.1.dist-info/WHEEL
fleece-1.2.1.dist-info/METADATA
fleece-1.2.1.dist-info/RECORD
