Metadata-Version: 2.1
Name: fleece
Version: 1.2.1
Summary: Wrap the lamb...da
Home-page: https://github.com/rackerlabs/fleece
License: Apache-2.0
Keywords: fleece,lambda
Author: Bruce Stringer
Author-email: bruce.stringer@rackspace.com
Maintainer: Bruce Stringer
Maintainer-email: bruce.stringer@rackspace.com
Requires-Python: >=3.6,<4.0
Classifier: Intended Audience :: Developers
Classifier: License :: OSI Approved :: Apache Software License
Classifier: Operating System :: OS Independent
Classifier: Programming Language :: Python
Classifier: Programming Language :: Python :: 3
Classifier: Programming Language :: Python :: 3.6
Classifier: Programming Language :: Python :: 3.7
Classifier: Programming Language :: Python :: 3.8
Classifier: Programming Language :: Python :: 3.9
Classifier: Programming Language :: Python :: 3.10
Classifier: Programming Language :: Python :: 3.11
Classifier: Programming Language :: Python :: 3
Classifier: Programming Language :: Python :: 3.6
Classifier: Programming Language :: Python :: 3.7
Classifier: Programming Language :: Python :: 3.8
Classifier: Topic :: Software Development
Provides-Extra: cli
Provides-Extra: connexion
Provides-Extra: wsgi
Requires-Dist: Flask (>=1.1.1); extra == "connexion"
Requires-Dist: PyYAML (>=3.12); extra == "cli"
Requires-Dist: Werkzeug (>=0.15.5); extra == "connexion" or extra == "wsgi"
Requires-Dist: boto3 (>=1.0.0)
Requires-Dist: connexion (>=1.1.9); extra == "connexion"
Requires-Dist: docker (>=3.5.1); extra == "cli"
Requires-Dist: requests (>=2.9.1)
Requires-Dist: ruamel.yaml (>=0.15.34); extra == "cli"
Requires-Dist: structlog (>=15.3.0)
Requires-Dist: wrapt (>=1.10.10)
Project-URL: Repository, https://github.com/rackerlabs/fleece
